Experimental/blinky.vhdl
library ieee;
use ieee.std_logic_1164.all;
use ieee.numeric_std.all;



entity blinker is
    generic(
        max_count : natural := 1_000_000
    );
    port(
        clk : in std_logic;
        led : out std_logic
    );
end blinker;

architecture Behavioural of blinker is
    signal counter : natural range 0 to max_count;
    signal s_led : std_logic := '0';
begin
    process(clk)
    begin
        if rising_edge(clk) then
            if counter = max_count then
                counter <= 0;
                s_led <= not s_led;
            else
                counter <= counter + 1;
            end if;
        end if;
    end process;
    led <= s_led;
end architecture;

Experimental/blinky_tb.vhdl
library ieee;
use ieee.std_logic_1164.all;
use ieee.numeric_std.all;


entity blinker_tb is
end entity;

architecture sim of blinker_tb is

component blinker is
    generic(
        max_count : natural := 1_000_000
    );
    port(
        clk : in std_logic;
        led : out std_logic
    );
end component;


    signal clk : std_logic := '0';
    signal led : std_logic;

    signal simDone : std_logic := '0';
    
    constant clk_period : time := 10 ns;

begin

    blinker_inst : blinker
    generic map(
        max_count => 100
    )
    port map(
        clk => clk,
        led => led
    );

    clk_gen : process is
    begin
        if simDone = '1' then
            wait;
        else
            wait for clk_period / 2;
            clk <= not clk;
        end if;
    end process;
       
    sim : process is
    begin
        wait for 100*10*5 ns;
        simDone <= '1';
        wait;
    end process;
    


end architecture;

Experimental/blinky.vcd
$date
  Sun Dec 31 21:59:50 2023
$end
$version
  GHDL v0
$end
$timescale
  1 fs
$end
$scope module standard $end
$upscope $end
$scope module std_logic_1164 $end
$upscope $end
$scope module numeric_std $end
$upscope $end
$scope module blinker_tb $end
$var reg 1 ! clk $end
$var reg 1 " led $end
$var reg 1 # simdone $end
$scope module blinker_inst $end
$var reg 1 $ clk $end
$var reg 1 % led $end
$var integer 32 & counter $end
$var reg 1 ' s_led $end
$upscope $end
$upscope $end
$enddefinitions $end
#0
0!
0"
0#
0$
0%
b0 &
0'
#5000000
1!
1$
b1 &
#10000000
0!
0$
#15000000
1!
1$
b10 &
#20000000
0!
0$
#25000000
1!
1$
b11 &
#30000000
0!
0$
#35000000
1!
1$
b100 &
#40000000
0!
0$
#45000000
1!
1$
b101 &
#50000000
0!
0$
#55000000
1!
1$
b110 &
#60000000
0!
0$
#65000000
1!
1$
b111 &
#70000000
0!
0$
#75000000
1!
1$
b1000 &
#80000000
0!
0$
#85000000
1!
1$
b1001 &
#90000000
0!
0$
#95000000
1!
1$
b1010 &
#100000000
0!
0$
#105000000
1!
1$
b1011 &
#110000000
0!
0$
#115000000
1!
1$
b1100 &
#120000000
0!
0$
#125000000
1!
1$
b1101 &
#130000000
0!
0$
#135000000
1!
1$
b1110 &
#140000000
0!
0$
#145000000
1!
1$
b1111 &
#150000000
0!
0$
#155000000
1!
1$
b10000 &
#160000000
0!
0$
#165000000
1!
1$
b10001 &
#170000000
0!
0$
#175000000
1!
1$
b10010 &
#180000000
0!
0$
#185000000
1!
1$
b10011 &
#190000000
0!
0$
#195000000
1!
1$
b10100 &
#200000000
0!
0$
#205000000
1!
1$
b10101 &
#210000000
0!
0$
#215000000
1!
1$
b10110 &
#220000000
0!
0$
#225000000
1!
1$
b10111 &
#230000000
0!
0$
#235000000
1!
1$
b11000 &
#240000000
0!
0$
#245000000
1!
1$
b11001 &
#250000000
0!
0$
#255000000
1!
1$
b11010 &
#260000000
0!
0$
#265000000
1!
1$
b11011 &
#270000000
0!
0$
#275000000
1!
1$
b11100 &
#280000000
0!
0$
#285000000
1!
1$
b11101 &
#290000000
0!
0$
#295000000
1!
1$
b11110 &
#300000000
0!
0$
#305000000
1!
1$
b11111 &
#310000000
0!
0$
#315000000
1!
1$
b100000 &
#320000000
0!
0$
#325000000
1!
1$
b100001 &
#330000000
0!
0$
#335000000
1!
1$
b100010 &
#340000000
0!
0$
#345000000
1!
1$
b100011 &
#350000000
0!
0$
#355000000
1!
1$
b100100 &
#360000000
0!
0$
#365000000
1!
1$
b100101 &
#370000000
0!
0$
#375000000
1!
1$
b100110 &
#380000000
0!
0$
#385000000
1!
1$
b100111 &
#390000000
0!
0$
#395000000
1!
1$
b101000 &
#400000000
0!
0$
#405000000
1!
1$
b101001 &
#410000000
0!
0$
#415000000
1!
1$
b101010 &
#420000000
0!
0$
#425000000
1!
1$
b101011 &
#430000000
0!
0$
#435000000
1!
1$
b101100 &
#440000000
0!
0$
#445000000
1!
1$
b101101 &
#450000000
0!
0$
#455000000
1!
1$
b101110 &
#460000000
0!
0$
#465000000
1!
1$
b101111 &
#470000000
0!
0$
#475000000
1!
1$
b110000 &
#480000000
0!
0$
#485000000
1!
1$
b110001 &
#490000000
0!
0$
#495000000
1!
1$
b110010 &
#500000000
0!
0$
#505000000
1!
1$
b110011 &
#510000000
0!
0$
#515000000
1!
1$
b110100 &
#520000000
0!
0$
#525000000
1!
1$
b110101 &
#530000000
0!
0$
#535000000
1!
1$
b110110 &
#540000000
0!
0$
#545000000
1!
1$
b110111 &
#550000000
0!
0$
#555000000
1!
1$
b111000 &
#560000000
0!
0$
#565000000
1!
1$
b111001 &
#570000000
0!
0$
#575000000
1!
1$
b111010 &
#580000000
0!
0$
#585000000
1!
1$
b111011 &
#590000000
0!
0$
#595000000
1!
1$
b111100 &
#600000000
0!
0$
#605000000
1!
1$
b111101 &
#610000000
0!
0$
#615000000
1!
1$
b111110 &
#620000000
0!
0$
#625000000
1!
1$
b111111 &
#630000000
0!
0$
#635000000
1!
1$
b1000000 &
#640000000
0!
0$
#645000000
1!
1$
b1000001 &
#650000000
0!
0$
#655000000
1!
1$
b1000010 &
#660000000
0!
0$
#665000000
1!
1$
b1000011 &
#670000000
0!
0$
#675000000
1!
1$
b1000100 &
#680000000
0!
0$
#685000000
1!
1$
b1000101 &
#690000000
0!
0$
#695000000
1!
1$
b1000110 &
#700000000
0!
0$
#705000000
1!
1$
b1000111 &
#710000000
0!
0$
#715000000
1!
1$
b1001000 &
#720000000
0!
0$
#725000000
1!
1$
b1001001 &
#730000000
0!
0$
#735000000
1!
1$
b1001010 &
#740000000
0!
0$
#745000000
1!
1$
b1001011 &
#750000000
0!
0$
#755000000
1!
1$
b1001100 &
#760000000
0!
0$
#765000000
1!
1$
b1001101 &
#770000000
0!
0$
#775000000
1!
1$
b1001110 &
#780000000
0!
0$
#785000000
1!
1$
b1001111 &
#790000000
0!
0$
#795000000
1!
1$
b1010000 &
#800000000
0!
0$
#805000000
1!
1$
b1010001 &
#810000000
0!
0$
#815000000
1!
1$
b1010010 &
#820000000
0!
0$
#825000000
1!
1$
b1010011 &
#830000000
0!
0$
#835000000
1!
1$
b1010100 &
#840000000
0!
0$
#845000000
1!
1$
b1010101 &
#850000000
0!
0$
#855000000
1!
1$
b1010110 &
#860000000
0!
0$
#865000000
1!
1$
b1010111 &
#870000000
0!
0$
#875000000
1!
1$
b1011000 &
#880000000
0!
0$
#885000000
1!
1$
b1011001 &
#890000000
0!
0$
#895000000
1!
1$
b1011010 &
#900000000
0!
0$
#905000000
1!
1$
b1011011 &
#910000000
0!
0$
#915000000
1!
1$
b1011100 &
#920000000
0!
0$
#925000000
1!
1$
b1011101 &
#930000000
0!
0$
#935000000
1!
1$
b1011110 &
#940000000
0!
0$
#945000000
1!
1$
b1011111 &
#950000000
0!
0$
#955000000
1!
1$
b1100000 &
#960000000
0!
0$
#965000000
1!
1$
b1100001 &
#970000000
0!
0$
#975000000
1!
1$
b1100010 &
#980000000
0!
0$
#985000000
1!
1$
b1100011 &
#990000000
0!
0$
#995000000
1!
1$
b1100100 &
#1000000000
0!
0$
#1005000000
1!
1"
1$
1%
b0 &
1'
#1010000000
0!
0$
#1015000000
1!
1$
b1 &
#1020000000
0!
0$
#1025000000
1!
1$
b10 &
#1030000000
0!
0$
#1035000000
1!
1$
b11 &
#1040000000
0!
0$
#1045000000
1!
1$
b100 &
#1050000000
0!
0$
#1055000000
1!
1$
b101 &
#1060000000
0!
0$
#1065000000
1!
1$
b110 &
#1070000000
0!
0$
#1075000000
1!
1$
b111 &
#1080000000
0!
0$
#1085000000
1!
1$
b1000 &
#1090000000
0!
0$
#1095000000
1!
1$
b1001 &
#1100000000
0!
0$
#1105000000
1!
1$
b1010 &
#1110000000
0!
0$
#1115000000
1!
1$
b1011 &
#1120000000
0!
0$
#1125000000
1!
1$
b1100 &
#1130000000
0!
0$
#1135000000
1!
1$
b1101 &
#1140000000
0!
0$
#1145000000
1!
1$
b1110 &
#1150000000
0!
0$
#1155000000
1!
1$
b1111 &
#1160000000
0!
0$
#1165000000
1!
1$
b10000 &
#1170000000
0!
0$
#1175000000
1!
1$
b10001 &
#1180000000
0!
0$
#1185000000
1!
1$
b10010 &
#1190000000
0!
0$
#1195000000
1!
1$
b10011 &
#1200000000
0!
0$
#1205000000
1!
1$
b10100 &
#1210000000
0!
0$
#1215000000
1!
1$
b10101 &
#1220000000
0!
0$
#1225000000
1!
1$
b10110 &
#1230000000
0!
0$
#1235000000
1!
1$
b10111 &
#1240000000
0!
0$
#1245000000
1!
1$
b11000 &
#1250000000
0!
0$
#1255000000
1!
1$
b11001 &
#1260000000
0!
0$
#1265000000
1!
1$
b11010 &
#1270000000
0!
0$
#1275000000
1!
1$
b11011 &
#1280000000
0!
0$
#1285000000
1!
1$
b11100 &
#1290000000
0!
0$
#1295000000
1!
1$
b11101 &
#1300000000
0!
0$
#1305000000
1!
1$
b11110 &
#1310000000
0!
0$
#1315000000
1!
1$
b11111 &
#1320000000
0!
0$
#1325000000
1!
1$
b100000 &
#1330000000
0!
0$
#1335000000
1!
1$
b100001 &
#1340000000
0!
0$
#1345000000
1!
1$
b100010 &
#1350000000
0!
0$
#1355000000
1!
1$
b100011 &
#1360000000
0!
0$
#1365000000
1!
1$
b100100 &
#1370000000
0!
0$
#1375000000
1!
1$
b100101 &
#1380000000
0!
0$
#1385000000
1!
1$
b100110 &
#1390000000
0!
0$
#1395000000
1!
1$
b100111 &
#1400000000
0!
0$
#1405000000
1!
1$
b101000 &
#1410000000
0!
0$
#1415000000
1!
1$
b101001 &
#1420000000
0!
0$
#1425000000
1!
1$
b101010 &
#1430000000
0!
0$
#1435000000
1!
1$
b101011 &
#1440000000
0!
0$
#1445000000
1!
1$
b101100 &
#1450000000
0!
0$
#1455000000
1!
1$
b101101 &
#1460000000
0!
0$
#1465000000
1!
1$
b101110 &
#1470000000
0!
0$
#1475000000
1!
1$
b101111 &
#1480000000
0!
0$
#1485000000
1!
1$
b110000 &
#1490000000
0!
0$
#1495000000
1!
1$
b110001 &
#1500000000
0!
0$
#1505000000
1!
1$
b110010 &
#1510000000
0!
0$
#1515000000
1!
1$
b110011 &
#1520000000
0!
0$
#1525000000
1!
1$
b110100 &
#1530000000
0!
0$
#1535000000
1!
1$
b110101 &
#1540000000
0!
0$
#1545000000
1!
1$
b110110 &
#1550000000
0!
0$
#1555000000
1!
1$
b110111 &
#1560000000
0!
0$
#1565000000
1!
1$
b111000 &
#1570000000
0!
0$
#1575000000
1!
1$
b111001 &
#1580000000
0!
0$
#1585000000
1!
1$
b111010 &
#1590000000
0!
0$
#1595000000
1!
1$
b111011 &
#1600000000
0!
0$
#1605000000
1!
1$
b111100 &
#1610000000
0!
0$
#1615000000
1!
1$
b111101 &
#1620000000
0!
0$
#1625000000
1!
1$
b111110 &
#1630000000
0!
0$
#1635000000
1!
1$
b111111 &
#1640000000
0!
0$
#1645000000
1!
1$
b1000000 &
#1650000000
0!
0$
#1655000000
1!
1$
b1000001 &
#1660000000
0!
0$
#1665000000
1!
1$
b1000010 &
#1670000000
0!
0$
#1675000000
1!
1$
b1000011 &
#1680000000
0!
0$
#1685000000
1!
1$
b1000100 &
#1690000000
0!
0$
#1695000000
1!
1$
b1000101 &
#1700000000
0!
0$
#1705000000
1!
1$
b1000110 &
#1710000000
0!
0$
#1715000000
1!
1$
b1000111 &
#1720000000
0!
0$
#1725000000
1!
1$
b1001000 &
#1730000000
0!
0$
#1735000000
1!
1$
b1001001 &
#1740000000
0!
0$
#1745000000
1!
1$
b1001010 &
#1750000000
0!
0$
#1755000000
1!
1$
b1001011 &
#1760000000
0!
0$
#1765000000
1!
1$
b1001100 &
#1770000000
0!
0$
#1775000000
1!
1$
b1001101 &
#1780000000
0!
0$
#1785000000
1!
1$
b1001110 &
#1790000000
0!
0$
#1795000000
1!
1$
b1001111 &
#1800000000
0!
0$
#1805000000
1!
1$
b1010000 &
#1810000000
0!
0$
#1815000000
1!
1$
b1010001 &
#1820000000
0!
0$
#1825000000
1!
1$
b1010010 &
#1830000000
0!
0$
#1835000000
1!
1$
b1010011 &
#1840000000
0!
0$
#1845000000
1!
1$
b1010100 &
#1850000000
0!
0$
#1855000000
1!
1$
b1010101 &
#1860000000
0!
0$
#1865000000
1!
1$
b1010110 &
#1870000000
0!
0$
#1875000000
1!
1$
b1010111 &
#1880000000
0!
0$
#1885000000
1!
1$
b1011000 &
#1890000000
0!
0$
#1895000000
1!
1$
b1011001 &
#1900000000
0!
0$
#1905000000
1!
1$
b1011010 &
#1910000000
0!
0$
#1915000000
1!
1$
b1011011 &
#1920000000
0!
0$
#1925000000
1!
1$
b1011100 &
#1930000000
0!
0$
#1935000000
1!
1$
b1011101 &
#1940000000
0!
0$
#1945000000
1!
1$
b1011110 &
#1950000000
0!
0$
#1955000000
1!
1$
b1011111 &
#1960000000
0!
0$
#1965000000
1!
1$
b1100000 &
#1970000000
0!
0$
#1975000000
1!
1$
b1100001 &
#1980000000
0!
0$
#1985000000
1!
1$
b1100010 &
#1990000000
0!
0$
#1995000000
1!
1$
b1100011 &
#2000000000
0!
0$
#2005000000
1!
1$
b1100100 &
#2010000000
0!
0$
#2015000000
1!
0"
1$
0%
b0 &
0'
#2020000000
0!
0$
#2025000000
1!
1$
b1 &
#2030000000
0!
0$
#2035000000
1!
1$
b10 &
#2040000000
0!
0$
#2045000000
1!
1$
b11 &
#2050000000
0!
0$
#2055000000
1!
1$
b100 &
#2060000000
0!
0$
#2065000000
1!
1$
b101 &
#2070000000
0!
0$
#2075000000
1!
1$
b110 &
#2080000000
0!
0$
#2085000000
1!
1$
b111 &
#2090000000
0!
0$
#2095000000
1!
1$
b1000 &
#2100000000
0!
0$
#2105000000
1!
1$
b1001 &
#2110000000
0!
0$
#2115000000
1!
1$
b1010 &
#2120000000
0!
0$
#2125000000
1!
1$
b1011 &
#2130000000
0!
0$
#2135000000
1!
1$
b1100 &
#2140000000
0!
0$
#2145000000
1!
1$
b1101 &
#2150000000
0!
0$
#2155000000
1!
1$
b1110 &
#2160000000
0!
0$
#2165000000
1!
1$
b1111 &
#2170000000
0!
0$
#2175000000
1!
1$
b10000 &
#2180000000
0!
0$
#2185000000
1!
1$
b10001 &
#2190000000
0!
0$
#2195000000
1!
1$
b10010 &
#2200000000
0!
0$
#2205000000
1!
1$
b10011 &
#2210000000
0!
0$
#2215000000
1!
1$
b10100 &
#2220000000
0!
0$
#2225000000
1!
1$
b10101 &
#2230000000
0!
0$
#2235000000
1!
1$
b10110 &
#2240000000
0!
0$
#2245000000
1!
1$
b10111 &
#2250000000
0!
0$
#2255000000
1!
1$
b11000 &
#2260000000
0!
0$
#2265000000
1!
1$
b11001 &
#2270000000
0!
0$
#2275000000
1!
1$
b11010 &
#2280000000
0!
0$
#2285000000
1!
1$
b11011 &
#2290000000
0!
0$
#2295000000
1!
1$
b11100 &
#2300000000
0!
0$
#2305000000
1!
1$
b11101 &
#2310000000
0!
0$
#2315000000
1!
1$
b11110 &
#2320000000
0!
0$
#2325000000
1!
1$
b11111 &
#2330000000
0!
0$
#2335000000
1!
1$
b100000 &
#2340000000
0!
0$
#2345000000
1!
1$
b100001 &
#2350000000
0!
0$
#2355000000
1!
1$
b100010 &
#2360000000
0!
0$
#2365000000
1!
1$
b100011 &
#2370000000
0!
0$
#2375000000
1!
1$
b100100 &
#2380000000
0!
0$
#2385000000
1!
1$
b100101 &
#2390000000
0!
0$
#2395000000
1!
1$
b100110 &
#2400000000
0!
0$
#2405000000
1!
1$
b100111 &
#2410000000
0!
0$
#2415000000
1!
1$
b101000 &
#2420000000
0!
0$
#2425000000
1!
1$
b101001 &
#2430000000
0!
0$
#2435000000
1!
1$
b101010 &
#2440000000
0!
0$
#2445000000
1!
1$
b101011 &
#2450000000
0!
0$
#2455000000
1!
1$
b101100 &
#2460000000
0!
0$
#2465000000
1!
1$
b101101 &
#2470000000
0!
0$
#2475000000
1!
1$
b101110 &
#2480000000
0!
0$
#2485000000
1!
1$
b101111 &
#2490000000
0!
0$
#2495000000
1!
1$
b110000 &
#2500000000
0!
0$
#2505000000
1!
1$
b110001 &
#2510000000
0!
0$
#2515000000
1!
1$
b110010 &
#2520000000
0!
0$
#2525000000
1!
1$
b110011 &
#2530000000
0!
0$
#2535000000
1!
1$
b110100 &
#2540000000
0!
0$
#2545000000
1!
1$
b110101 &
#2550000000
0!
0$
#2555000000
1!
1$
b110110 &
#2560000000
0!
0$
#2565000000
1!
1$
b110111 &
#2570000000
0!
0$
#2575000000
1!
1$
b111000 &
#2580000000
0!
0$
#2585000000
1!
1$
b111001 &
#2590000000
0!
0$
#2595000000
1!
1$
b111010 &
#2600000000
0!
0$
#2605000000
1!
1$
b111011 &
#2610000000
0!
0$
#2615000000
1!
1$
b111100 &
#2620000000
0!
0$
#2625000000
1!
1$
b111101 &
#2630000000
0!
0$
#2635000000
1!
1$
b111110 &
#2640000000
0!
0$
#2645000000
1!
1$
b111111 &
#2650000000
0!
0$
#2655000000
1!
1$
b1000000 &
#2660000000
0!
0$
#2665000000
1!
1$
b1000001 &
#2670000000
0!
0$
#2675000000
1!
1$
b1000010 &
#2680000000
0!
0$
#2685000000
1!
1$
b1000011 &
#2690000000
0!
0$
#2695000000
1!
1$
b1000100 &
#2700000000
0!
0$
#2705000000
1!
1$
b1000101 &
#2710000000
0!
0$
#2715000000
1!
1$
b1000110 &
#2720000000
0!
0$
#2725000000
1!
1$
b1000111 &
#2730000000
0!
0$
#2735000000
1!
1$
b1001000 &
#2740000000
0!
0$
#2745000000
1!
1$
b1001001 &
#2750000000
0!
0$
#2755000000
1!
1$
b1001010 &
#2760000000
0!
0$
#2765000000
1!
1$
b1001011 &
#2770000000
0!
0$
#2775000000
1!
1$
b1001100 &
#2780000000
0!
0$
#2785000000
1!
1$
b1001101 &
#2790000000
0!
0$
#2795000000
1!
1$
b1001110 &
#2800000000
0!
0$
#2805000000
1!
1$
b1001111 &
#2810000000
0!
0$
#2815000000
1!
1$
b1010000 &
#2820000000
0!
0$
#2825000000
1!
1$
b1010001 &
#2830000000
0!
0$
#2835000000
1!
1$
b1010010 &
#2840000000
0!
0$
#2845000000
1!
1$
b1010011 &
#2850000000
0!
0$
#2855000000
1!
1$
b1010100 &
#2860000000
0!
0$
#2865000000
1!
1$
b1010101 &
#2870000000
0!
0$
#2875000000
1!
1$
b1010110 &
#2880000000
0!
0$
#2885000000
1!
1$
b1010111 &
#2890000000
0!
0$
#2895000000
1!
1$
b1011000 &
#2900000000
0!
0$
#2905000000
1!
1$
b1011001 &
#2910000000
0!
0$
#2915000000
1!
1$
b1011010 &
#2920000000
0!
0$
#2925000000
1!
1$
b1011011 &
#2930000000
0!
0$
#2935000000
1!
1$
b1011100 &
#2940000000
0!
0$
#2945000000
1!
1$
b1011101 &
#2950000000
0!
0$
#2955000000
1!
1$
b1011110 &
#2960000000
0!
0$
#2965000000
1!
1$
b1011111 &
#2970000000
0!
0$
#2975000000
1!
1$
b1100000 &
#2980000000
0!
0$
#2985000000
1!
1$
b1100001 &
#2990000000
0!
0$
#2995000000
1!
1$
b1100010 &
#3000000000
0!
0$
#3005000000
1!
1$
b1100011 &
#3010000000
0!
0$
#3015000000
1!
1$
b1100100 &
#3020000000
0!
0$
#3025000000
1!
1"
1$
1%
b0 &
1'
#3030000000
0!
0$
#3035000000
1!
1$
b1 &
#3040000000
0!
0$
#3045000000
1!
1$
b10 &
#3050000000
0!
0$
#3055000000
1!
1$
b11 &
#3060000000
0!
0$
#3065000000
1!
1$
b100 &
#3070000000
0!
0$
#3075000000
1!
1$
b101 &
#3080000000
0!
0$
#3085000000
1!
1$
b110 &
#3090000000
0!
0$
#3095000000
1!
1$
b111 &
#3100000000
0!
0$
#3105000000
1!
1$
b1000 &
#3110000000
0!
0$
#3115000000
1!
1$
b1001 &
#3120000000
0!
0$
#3125000000
1!
1$
b1010 &
#3130000000
0!
0$
#3135000000
1!
1$
b1011 &
#3140000000
0!
0$
#3145000000
1!
1$
b1100 &
#3150000000
0!
0$
#3155000000
1!
1$
b1101 &
#3160000000
0!
0$
#3165000000
1!
1$
b1110 &
#3170000000
0!
0$
#3175000000
1!
1$
b1111 &
#3180000000
0!
0$
#3185000000
1!
1$
b10000 &
#3190000000
0!
0$
#3195000000
1!
1$
b10001 &
#3200000000
0!
0$
#3205000000
1!
1$
b10010 &
#3210000000
0!
0$
#3215000000
1!
1$
b10011 &
#3220000000
0!
0$
#3225000000
1!
1$
b10100 &
#3230000000
0!
0$
#3235000000
1!
1$
b10101 &
#3240000000
0!
0$
#3245000000
1!
1$
b10110 &
#3250000000
0!
0$
#3255000000
1!
1$
b10111 &
#3260000000
0!
0$
#3265000000
1!
1$
b11000 &
#3270000000
0!
0$
#3275000000
1!
1$
b11001 &
#3280000000
0!
0$
#3285000000
1!
1$
b11010 &
#3290000000
0!
0$
#3295000000
1!
1$
b11011 &
#3300000000
0!
0$
#3305000000
1!
1$
b11100 &
#3310000000
0!
0$
#3315000000
1!
1$
b11101 &
#3320000000
0!
0$
#3325000000
1!
1$
b11110 &
#3330000000
0!
0$
#3335000000
1!
1$
b11111 &
#3340000000
0!
0$
#3345000000
1!
1$
b100000 &
#3350000000
0!
0$
#3355000000
1!
1$
b100001 &
#3360000000
0!
0$
#3365000000
1!
1$
b100010 &
#3370000000
0!
0$
#3375000000
1!
1$
b100011 &
#3380000000
0!
0$
#3385000000
1!
1$
b100100 &
#3390000000
0!
0$
#3395000000
1!
1$
b100101 &
#3400000000
0!
0$
#3405000000
1!
1$
b100110 &
#3410000000
0!
0$
#3415000000
1!
1$
b100111 &
#3420000000
0!
0$
#3425000000
1!
1$
b101000 &
#3430000000
0!
0$
#3435000000
1!
1$
b101001 &
#3440000000
0!
0$
#3445000000
1!
1$
b101010 &
#3450000000
0!
0$
#3455000000
1!
1$
b101011 &
#3460000000
0!
0$
#3465000000
1!
1$
b101100 &
#3470000000
0!
0$
#3475000000
1!
1$
b101101 &
#3480000000
0!
0$
#3485000000
1!
1$
b101110 &
#3490000000
0!
0$
#3495000000
1!
1$
b101111 &
#3500000000
0!
0$
#3505000000
1!
1$
b110000 &
#3510000000
0!
0$
#3515000000
1!
1$
b110001 &
#3520000000
0!
0$
#3525000000
1!
1$
b110010 &
#3530000000
0!
0$
#3535000000
1!
1$
b110011 &
#3540000000
0!
0$
#3545000000
1!
1$
b110100 &
#3550000000
0!
0$
#3555000000
1!
1$
b110101 &
#3560000000
0!
0$
#3565000000
1!
1$
b110110 &
#3570000000
0!
0$
#3575000000
1!
1$
b110111 &
#3580000000
0!
0$
#3585000000
1!
1$
b111000 &
#3590000000
0!
0$
#3595000000
1!
1$
b111001 &
#3600000000
0!
0$
#3605000000
1!
1$
b111010 &
#3610000000
0!
0$
#3615000000
1!
1$
b111011 &
#3620000000
0!
0$
#3625000000
1!
1$
b111100 &
#3630000000
0!
0$
#3635000000
1!
1$
b111101 &
#3640000000
0!
0$
#3645000000
1!
1$
b111110 &
#3650000000
0!
0$
#3655000000
1!
1$
b111111 &
#3660000000
0!
0$
#3665000000
1!
1$
b1000000 &
#3670000000
0!
0$
#3675000000
1!
1$
b1000001 &
#3680000000
0!
0$
#3685000000
1!
1$
b1000010 &
#3690000000
0!
0$
#3695000000
1!
1$
b1000011 &
#3700000000
0!
0$
#3705000000
1!
1$
b1000100 &
#3710000000
0!
0$
#3715000000
1!
1$
b1000101 &
#3720000000
0!
0$
#3725000000
1!
1$
b1000110 &
#3730000000
0!
0$
#3735000000
1!
1$
b1000111 &
#3740000000
0!
0$
#3745000000
1!
1$
b1001000 &
#3750000000
0!
0$
#3755000000
1!
1$
b1001001 &
#3760000000
0!
0$
#3765000000
1!
1$
b1001010 &
#3770000000
0!
0$
#3775000000
1!
1$
b1001011 &
#3780000000
0!
0$
#3785000000
1!
1$
b1001100 &
#3790000000
0!
0$
#3795000000
1!
1$
b1001101 &
#3800000000
0!
0$
#3805000000
1!
1$
b1001110 &
#3810000000
0!
0$
#3815000000
1!
1$
b1001111 &
#3820000000
0!
0$
#3825000000
1!
1$
b1010000 &
#3830000000
0!
0$
#3835000000
1!
1$
b1010001 &
#3840000000
0!
0$
#3845000000
1!
1$
b1010010 &
#3850000000
0!
0$
#3855000000
1!
1$
b1010011 &
#3860000000
0!
0$
#3865000000
1!
1$
b1010100 &
#3870000000
0!
0$
#3875000000
1!
1$
b1010101 &
#3880000000
0!
0$
#3885000000
1!
1$
b1010110 &
#3890000000
0!
0$
#3895000000
1!
1$
b1010111 &
#3900000000
0!
0$
#3905000000
1!
1$
b1011000 &
#3910000000
0!
0$
#3915000000
1!
1$
b1011001 &
#3920000000
0!
0$
#3925000000
1!
1$
b1011010 &
#3930000000
0!
0$
#3935000000
1!
1$
b1011011 &
#3940000000
0!
0$
#3945000000
1!
1$
b1011100 &
#3950000000
0!
0$
#3955000000
1!
1$
b1011101 &
#3960000000
0!
0$
#3965000000
1!
1$
b1011110 &
#3970000000
0!
0$
#3975000000
1!
1$
b1011111 &
#3980000000
0!
0$
#3985000000
1!
1$
b1100000 &
#3990000000
0!
0$
#3995000000
1!
1$
b1100001 &
#4000000000
0!
0$
#4005000000
1!
1$
b1100010 &
#4010000000
0!
0$
#4015000000
1!
1$
b1100011 &
#4020000000
0!
0$
#4025000000
1!
1$
b1100100 &
#4030000000
0!
0$
#4035000000
1!
0"
1$
0%
b0 &
0'
#4040000000
0!
0$
#4045000000
1!
1$
b1 &
#4050000000
0!
0$
#4055000000
1!
1$
b10 &
#4060000000
0!
0$
#4065000000
1!
1$
b11 &
#4070000000
0!
0$
#4075000000
1!
1$
b100 &
#4080000000
0!
0$
#4085000000
1!
1$
b101 &
#4090000000
0!
0$
#4095000000
1!
1$
b110 &
#4100000000
0!
0$
#4105000000
1!
1$
b111 &
#4110000000
0!
0$
#4115000000
1!
1$
b1000 &
#4120000000
0!
0$
#4125000000
1!
1$
b1001 &
#4130000000
0!
0$
#4135000000
1!
1$
b1010 &
#4140000000
0!
0$
#4145000000
1!
1$
b1011 &
#4150000000
0!
0$
#4155000000
1!
1$
b1100 &
#4160000000
0!
0$
#4165000000
1!
1$
b1101 &
#4170000000
0!
0$
#4175000000
1!
1$
b1110 &
#4180000000
0!
0$
#4185000000
1!
1$
b1111 &
#4190000000
0!
0$
#4195000000
1!
1$
b10000 &
#4200000000
0!
0$
#4205000000
1!
1$
b10001 &
#4210000000
0!
0$
#4215000000
1!
1$
b10010 &
#4220000000
0!
0$
#4225000000
1!
1$
b10011 &
#4230000000
0!
0$
#4235000000
1!
1$
b10100 &
#4240000000
0!
0$
#4245000000
1!
1$
b10101 &
#4250000000
0!
0$
#4255000000
1!
1$
b10110 &
#4260000000
0!
0$
#4265000000
1!
1$
b10111 &
#4270000000
0!
0$
#4275000000
1!
1$
b11000 &
#4280000000
0!
0$
#4285000000
1!
1$
b11001 &
#4290000000
0!
0$
#4295000000
1!
1$
b11010 &
#4300000000
0!
0$
#4305000000
1!
1$
b11011 &
#4310000000
0!
0$
#4315000000
1!
1$
b11100 &
#4320000000
0!
0$
#4325000000
1!
1$
b11101 &
#4330000000
0!
0$
#4335000000
1!
1$
b11110 &
#4340000000
0!
0$
#4345000000
1!
1$
b11111 &
#4350000000
0!
0$
#4355000000
1!
1$
b100000 &
#4360000000
0!
0$
#4365000000
1!
1$
b100001 &
#4370000000
0!
0$
#4375000000
1!
1$
b100010 &
#4380000000
0!
0$
#4385000000
1!
1$
b100011 &
#4390000000
0!
0$
#4395000000
1!
1$
b100100 &
#4400000000
0!
0$
#4405000000
1!
1$
b100101 &
#4410000000
0!
0$
#4415000000
1!
1$
b100110 &
#4420000000
0!
0$
#4425000000
1!
1$
b100111 &
#4430000000
0!
0$
#4435000000
1!
1$
b101000 &
#4440000000
0!
0$
#4445000000
1!
1$
b101001 &
#4450000000
0!
0$
#4455000000
1!
1$
b101010 &
#4460000000
0!
0$
#4465000000
1!
1$
b101011 &
#4470000000
0!
0$
#4475000000
1!
1$
b101100 &
#4480000000
0!
0$
#4485000000
1!
1$
b101101 &
#4490000000
0!
0$
#4495000000
1!
1$
b101110 &
#4500000000
0!
0$
#4505000000
1!
1$
b101111 &
#4510000000
0!
0$
#4515000000
1!
1$
b110000 &
#4520000000
0!
0$
#4525000000
1!
1$
b110001 &
#4530000000
0!
0$
#4535000000
1!
1$
b110010 &
#4540000000
0!
0$
#4545000000
1!
1$
b110011 &
#4550000000
0!
0$
#4555000000
1!
1$
b110100 &
#4560000000
0!
0$
#4565000000
1!
1$
b110101 &
#4570000000
0!
0$
#4575000000
1!
1$
b110110 &
#4580000000
0!
0$
#4585000000
1!
1$
b110111 &
#4590000000
0!
0$
#4595000000
1!
1$
b111000 &
#4600000000
0!
0$
#4605000000
1!
1$
b111001 &
#4610000000
0!
0$
#4615000000
1!
1$
b111010 &
#4620000000
0!
0$
#4625000000
1!
1$
b111011 &
#4630000000
0!
0$
#4635000000
1!
1$
b111100 &
#4640000000
0!
0$
#4645000000
1!
1$
b111101 &
#4650000000
0!
0$
#4655000000
1!
1$
b111110 &
#4660000000
0!
0$
#4665000000
1!
1$
b111111 &
#4670000000
0!
0$
#4675000000
1!
1$
b1000000 &
#4680000000
0!
0$
#4685000000
1!
1$
b1000001 &
#4690000000
0!
0$
#4695000000
1!
1$
b1000010 &
#4700000000
0!
0$
